dask_quik/__init__.py
dask_quik/cartesian.py
dask_quik/combine.py
dask_quik/dummy.py
dask_quik/split.py
dask_quik/transform.py
dask_quik/utils.py
dask_quik/tests/__init__.py
dask_quik/tests/conftest.py
dask_quik/tests/test_cartesian.py
dask_quik/tests/test_combine.py
dask_quik/tests/test_dataframes.py
dask_quik/tests/test_transform.py
dask_quik/tests/test_utils.py
dask_quik-0.0.4.dist-info/LICENSE
dask_quik-0.0.4.dist-info/METADATA
dask_quik-0.0.4.dist-info/WHEEL
dask_quik-0.0.4.dist-info/top_level.txt
dask_quik-0.0.4.dist-info/RECORD
