Metadata-Version: 2.1
Name: dask-quik
Version: 0.0.4
Summary: function to make working in dask_cudf and dask quik-er
Home-page: https://github.com/donchesworth/dask-quik
Author: Don Chesworth
Author-email: donald.chesworth@gmail.com
License: BSD
Platform: UNKNOWN
Classifier: License :: OSI Approved :: BSD License
Classifier: Programming Language :: Python :: 3.8
Requires-Dist: dask (>=2.29.0)
Requires-Dist: distributed (>=2.29.0)
Requires-Dist: pandas (>=1.1)
Requires-Dist: dask-ml
Requires-Dist: pytest
Requires-Dist: pytest-cov
Requires-Dist: codecov
Requires-Dist: bump2version
